LAB-02/lab2.v
// pipelined fast multiplier
module mult_fast(
	output reg[7:0] P,  // product
	input[3:0] A, B,    // multiplicand and multiplier
	input clk		    // clock (posedge)
	);
	// stage 0 (input)
	reg[3:0] a_s0, b_s0;
	always @(posedge clk) begin
		a_s0 <= A;
		b_s0 <= B;
	end
	// stage 1
	wire[3:0] pp0 = a_s0 & {4{b_s0[0]}}; // ignore the delays of AND gates
	wire[4:1] pp1 = a_s0 & {4{b_s0[1]}}; // ignore the delays of AND gates
	wire[5:2] pp2 = a_s0 & {4{b_s0[2]}}; // ignore the delays of AND gates
	wire[6:3] pp3 = a_s0 & {4{b_s0[3]}}; // ignore the delays of AND gates
	reg[5:1] sum1;
	always @(pp0, pp1)
		sum1[5:1] <= #7 pp0[3 : 1] + pp1[4 : 1]; // delay of the 4-bit adder
	reg[7:3] sum3;
	always @(pp2, pp3)
		sum3[7:3] <= #7 pp2[5 : 3] + pp3[6 : 3]; // delay of the 4-bit adder
	reg[5:0] sum1_s1;
	reg[7:2] sum3_s1;
	always @(posedge clk) begin
		sum1_s1 <= {sum1, pp0[0]};
		sum3_s1 <= {sum3, pp2[2]};
	end
	// stage 2 (outout)
	reg[7:2] sum2;
	always @(sum1_s1, sum3_s1)
		sum2[7:2] <= #8 sum1_s1[5 : 2] + sum3_s1[7 : 2]; // delay of the 6-bit adder
	always @(posedge clk) begin
		P <= {sum2, sum1_s1[1 : 0]};
	end
endmodule

// test bench
module mult_tb();
	// dump
	initial begin
		$dumpfile("lab2.vcd");
		$dumpvars(0, mult_tb);
	end
	// clock cycle = 10 ticks
	reg clock = 1;
	always
		#4 clock <= ~clock; /////////
	// multiplier
	reg[3:0] A, B;
	wire[7:0] P;
	reg[7:0] P_ref;
	mult_fast mult(P, A, B, clock);
	always @(posedge clock)
		P_ref <= #16 A*B; ///////////
	// loop through all possible inputs
	integer i;
	initial begin
		#9;
		for(i=0; i<256; i=i+1) begin
			{A, B} <= i;
			#8; ///////
		end
		#21 $finish;
	end
	// check if the products are correct
	reg[3:0] A_old, B_old;
	always @(posedge clock) begin
		#1
		if(P_ref!=P && i>=2) begin
			A_old = (i-2)/16;
			B_old = (i-2)%16;
			$display("Product is wrong when A=%b, B=%b.", A_old, B_old);
			$display("P_ref: %b.", P_ref);
			$display("P    : %b.", P);
			#9 $finish;
		end
	end
endmodule

LAB-02/lab2.vcd
$date
	Mon May 19 03:48:09 2025
$end
$version
	Icarus Verilog
$end
$timescale
	1s
$end
$scope module mult_tb $end
$var wire 8 ! P [7:0] $end
$var reg 4 " A [3:0] $end
$var reg 4 # A_old [3:0] $end
$var reg 4 $ B [3:0] $end
$var reg 4 % B_old [3:0] $end
$var reg 8 & P_ref [7:0] $end
$var reg 1 ' clock $end
$var integer 32 ( i [31:0] $end
$scope module mult $end
$var wire 4 ) A [3:0] $end
$var wire 4 * B [3:0] $end
$var wire 1 ' clk $end
$var wire 4 + pp0 [3:0] $end
$var wire 4 , pp1 [4:1] $end
$var wire 4 - pp2 [5:2] $end
$var wire 4 . pp3 [6:3] $end
$var reg 8 / P [7:0] $end
$var reg 4 0 a_s0 [3:0] $end
$var reg 4 1 b_s0 [3:0] $end
$var reg 5 2 sum1 [5:1] $end
$var reg 6 3 sum1_s1 [5:0] $end
$var reg 6 4 sum2 [7:2] $end
$var reg 5 5 sum3 [7:3] $end
$var reg 6 6 sum3_s1 [7:2] $end
$upscope $end
$upscope $end
$enddefinitions $end
#0
$dumpvars
bx 6
bx 5
bx 4
bx 3
bx 2
bx 1
bx 0
bx /
bx .
bx -
bx ,
bx +
bx *
bx )
bx (
1'
bx &
bx %
bx $
bx #
bx "
bx !
$end
#4
0'
#8
1'
#9
b0 "
b0 )
b0 $
b0 *
b0 (
#12
0'
#16
b0 .
b0 -
b0 ,
b0 +
b0 1
b0 0
1'
#17
b1 $
b1 *
b1 (
#20
0'
#23
b0 5
b0 2
#24
b0 6
b0 3
b1 1
1'
#25
b10 $
b10 *
b10 (
#28
0'
#32
b10 1
b0 !
b0 /
1'
b0 4
b0 &
#33
b11 $
b11 *
b11 (
#36
0'
#40
b11 1
1'
#41
b100 $
b100 *
b100 (
#44
0'
#48
b100 1
1'
#49
b101 $
b101 *
b101 (
#52
0'
#56
b101 1
1'
#57
b110 $
b110 *
b110 (
#60
0'
#64
b110 1
1'
#65
b111 $
b111 *
b111 (
#68
0'
#72
b111 1
1'
#73
b1000 $
b1000 *
b1000 (
#76
0'
#80
b1000 1
1'
#81
b1001 $
b1001 *
b1001 (
#84
0'
#88
b1001 1
1'
#89
b1010 $
b1010 *
b1010 (
#92
0'
#96
b1010 1
1'
#97
b1011 $
b1011 *
b1011 (
#100
0'
#104
b1011 1
1'
#105
b1100 $
b1100 *
b1100 (
#108
0'
#112
b1100 1
1'
#113
b1101 $
b1101 *
b1101 (
#116
0'
#120
b1101 1
1'
#121
b1110 $
b1110 *
b1110 (
#124
0'
#128
b1110 1
1'
#129
b1111 $
b1111 *
b1111 (
#132
0'
#136
b1111 1
1'
#137
b1 "
b1 )
b0 $
b0 *
b10000 (
#140
0'
#144
b0 .
b0 -
b0 ,
b0 +
b0 1
b1 0
1'
#145
b1 $
b1 *
b10001 (
#148
0'
#151
b0 5
b0 2
#152
b1 +
b1 1
1'
#153
b10 $
b10 *
b10010 (
#156
0'
#160
b0 +
b1 ,
b10 1
b1 3
1'
#161
b11 $
b11 *
b10011 (
#164
0'
#167
b1 2
#168
b1 +
b1 !
b1 /
b10 3
b11 1
1'
b1 &
#169
b100 $
b100 *
b10100 (
#172
0'
#176
b0 +
b0 ,
b1 -
b100 1
b11 3
b10 !
b10 /
1'
b10 &
#177
b101 $
b101 *
b10101 (
#180
0'
#183
b0 2
#184
b1 +
b11 !
b11 /
b1 6
b0 3
b101 1
1'
b11 &
#185
b110 $
b110 *
b10110 (
#188
0'
#192
b0 +
b1 ,
b110 1
b1 3
b100 !
b100 /
1'
b1 4
b100 &
#193
b111 $
b111 *
b10111 (
#196
0'
#199
b1 2
#200
b1 +
b101 !
b101 /
b10 3
b111 1
1'
b101 &
#201
b1000 $
b1000 *
b11000 (
#204
0'
#208
b0 +
b0 ,
b0 -
b1 .
b1000 1
b11 3
b110 !
b110 /
1'
b110 &
#209
b1001 $
b1001 *
b11001 (
#212
0'
#215
b0 2
b1 5
#216
b1 +
b111 !
b111 /
b10 6
b0 3
b1001 1
1'
b111 &
#217
b1010 $
b1010 *
b11010 (
#220
0'
#224
b0 +
b1 ,
b1010 1
b1 3
b1000 !
b1000 /
1'
b10 4
b1000 &
#225
b1011 $
b1011 *
b11011 (
#228
0'
#231
b1 2
#232
b1 +
b1001 !
b1001 /
b10 3
b1011 1
1'
b1001 &
#233
b1100 $
b1100 *
b11100 (
#236
0'
#240
b0 +
b0 ,
b1 -
b1100 1
b11 3
b1010 !
b1010 /
1'
b1010 &
#241
b1101 $
b1101 *
b11101 (
#244
0'
#247
b0 2
#248
b1 +
b1011 !
b1011 /
b11 6
b0 3
b1101 1
1'
b1011 &
#249
b1110 $
b1110 *
b11110 (
#252
0'
#256
b0 +
b1 ,
b1110 1
b1 3
b1100 !
b1100 /
1'
b11 4
b1100 &
#257
b1111 $
b1111 *
b11111 (
#260
0'
#263
b1 2
#264
b1 +
b1101 !
b1101 /
b10 3
b1111 1
1'
b1101 &
#265
b10 "
b10 )
b0 $
b0 *
b100000 (
#268
0'
#272
b0 .
b0 -
b0 ,
b0 +
b0 1
b10 0
b11 3
b1110 !
b1110 /
1'
b1110 &
#273
b1 $
b1 *
b100001 (
#276
0'
#279
b0 5
b0 2
#280
b10 +
b1111 !
b1111 /
b0 6
b0 3
b1 1
1'
b1111 &
#281
b10 $
b10 *
b100010 (
#284
0'
#287
b1 2
#288
b0 +
b10 ,
b10 1
b10 3
b0 !
b0 /
1'
b0 4
b0 &
#289
b11 $
b11 *
b100011 (
#292
0'
#295
b10 2
#296
b10 +
b10 !
b10 /
b100 3
b11 1
1'
b10 &
#297
b100 $
b100 *
b100100 (
#300
0'
#303
b11 2
#304
b0 +
b0 ,
b10 -
b100 1
b110 3
b100 !
b100 /
1'
b1 4
b100 &
#305
b101 $
b101 *
b100101 (
#308
0'
#311
b0 2
b1 5
#312
b10 +
b110 !
b110 /
b10 6
b0 3
b101 1
1'
b110 &
#313
b110 $
b110 *
b100110 (
#316
0'
#319
b1 2
#320
b0 +
b10 ,
b110 1
b10 3
b1000 !
b1000 /
1'
b10 4
b1000 &
#321
b111 $
b111 *
b100111 (
#324
0'
#327
b10 2
#328
b10 +
b1010 !
b1010 /
b100 3
b111 1
1'
b1010 &
#329
b1000 $
b1000 *
b101000 (
#332
0'
#335
b11 2
#336
b0 +
b0 ,
b0 -
b10 .
b1000 1
b110 3
b1100 !
b1100 /
1'
b11 4
b1100 &
#337
b1001 $
b1001 *
b101001 (
#340
0'
#343
b0 2
b10 5
#344
b10 +
b1110 !
b1110 /
b100 6
b0 3
b1001 1
1'
b1110 &
#345
b1010 $
b1010 *
b101010 (
#348
0'
#351
b1 2
#352
b0 +
b10 ,
b1010 1
b10 3
b10000 !
b10000 /
1'
b100 4
b10000 &
#353
b1011 $
b1011 *
b101011 (
#356
0'
#359
b10 2
#360
b10 +
b10010 !
b10010 /
b100 3
b1011 1
1'
b10010 &
#361
b1100 $
b1100 *
b101100 (
#364
0'
#367
b11 2
#368
b0 +
b0 ,
b10 -
b1100 1
b110 3
b10100 !
b10100 /
1'
b101 4
b10100 &
#369
b1101 $
b1101 *
b101101 (
#372
0'
#375
b0 2
b11 5
#376
b10 +
b10110 !
b10110 /
b110 6
b0 3
b1101 1
1'
b10110 &
#377
b1110 $
b1110 *
b101110 (
#380
0'
#383
b1 2
#384
b0 +
b10 ,
b1110 1
b10 3
b11000 !
b11000 /
1'
b110 4
b11000 &
#385
b1111 $
b1111 *
b101111 (
#388
0'
#391
b10 2
#392
b10 +
b11010 !
b11010 /
b100 3
b1111 1
1'
b11010 &
#393
b11 "
b11 )
b0 $
b0 *
b110000 (
#396
0'
#399
b11 2
#400
b0 .
b0 -
b0 ,
b0 +
b0 1
b11 0
b110 3
b11100 !
b11100 /
1'
b111 4
b11100 &
#401
b1 $
b1 *
b110001 (
#404
0'
#407
b0 5
b0 2
#408
b11 +
b11110 !
b11110 /
b0 6
b0 3
b1 1
1'
b11110 &
#409
b10 $
b10 *
b110010 (
#412
0'
#415
b1 2
#416
b0 +
b11 ,
b10 1
b11 3
b0 !
b0 /
1'
b0 4
b0 &
#417
b11 $
b11 *
b110011 (
#420
0'
#423
b11 2
#424
b11 +
b11 !
b11 /
b110 3
b11 1
1'
b11 &
#425
b100 $
b100 *
b110100 (
#428
0'
#431
b100 2
#432
b0 +
b0 ,
b11 -
b100 1
b1001 3
b110 !
b110 /
1'
b1 4
b110 &
#433
b101 $
b101 *
b110101 (
#436
0'
#439
b0 2
b1 5
#440
b11 +
b1001 !
b1001 /
b11 6
b0 3
b101 1
1'
b10 4
b1001 &
#441
b110 $
b110 *
b110110 (
#444
0'
#447
b1 2
#448
b0 +
b11 ,
b110 1
b11 3
b1100 !
b1100 /
1'
b11 4
b1100 &
#449
b111 $
b111 *
b110111 (
#452
0'
#455
b11 2
#456
b11 +
b1111 !
b1111 /
b110 3
b111 1
1'
b1111 &
#457
b1000 $
b1000 *
b111000 (
#460
0'
#463
b100 2
#464
b0 +
b0 ,
b0 -
b11 .
b1000 1
b1001 3
b10010 !
b10010 /
1'
b100 4
b10010 &
#465
b1001 $
b1001 *
b111001 (
#468
0'
#471
b0 2
b11 5
#472
b11 +
b10101 !
b10101 /
b110 6
b0 3
b1001 1
1'
b101 4
b10101 &
#473
b1010 $
b1010 *
b111010 (
#476
0'
#479
b1 2
#480
b0 +
b11 ,
b1010 1
b11 3
b11000 !
b11000 /
1'
b110 4
b11000 &
#481
b1011 $
b1011 *
b111011 (
#484
0'
#487
b11 2
#488
b11 +
b11011 !
b11011 /
b110 3
b1011 1
1'
b11011 &
#489
b1100 $
b1100 *
b111100 (
#492
0'
#495
b100 2
#496
b0 +
b0 ,
b11 -
b1100 1
b1001 3
b11110 !
b11110 /
1'
b111 4
b11110 &
#497
b1101 $
b1101 *
b111101 (
#500
0'
#503
b0 2
b100 5
#504
b11 +
b100001 !
b100001 /
b1001 6
b0 3
b1101 1
1'
b1000 4
b100001 &
#505
b1110 $
b1110 *
b111110 (
#508
0'
#511
b1 2
#512
b0 +
b11 ,
b1110 1
b11 3
b100100 !
b100100 /
1'
b1001 4
b100100 &
#513
b1111 $
b1111 *
b111111 (
#516
0'
#519
b11 2
#520
b11 +
b100111 !
b100111 /
b110 3
b1111 1
1'
b100111 &
#521
b100 "
b100 )
b0 $
b0 *
b1000000 (
#524
0'
#527
b100 2
#528
b0 .
b0 -
b0 ,
b0 +
b0 1
b100 0
b1001 3
b101010 !
b101010 /
1'
b1010 4
b101010 &
#529
b1 $
b1 *
b1000001 (
#532
0'
#535
b0 5
b0 2
#536
b100 +
b101101 !
b101101 /
b0 6
b0 3
b1 1
1'
b1011 4
b101101 &
#537
b10 $
b10 *
b1000010 (
#540
0'
#543
b10 2
#544
b0 +
b100 ,
b10 1
b100 3
b0 !
b0 /
1'
b0 4
b0 &
#545
b11 $
b11 *
b1000011 (
#548
0'
#551
b100 2
#552
b100 +
b100 !
b100 /
b1000 3
b11 1
1'
b1 4
b100 &
#553
b100 $
b100 *
b1000100 (
#556
0'
#559
b110 2
#560
b0 +
b0 ,
b100 -
b100 1
b1100 3
b1000 !
b1000 /
1'
b10 4
b1000 &
#561
b101 $
b101 *
b1000101 (
#564
0'
#567
b0 2
b10 5
#568
b100 +
b1100 !
b1100 /
b100 6
b0 3
b101 1
1'
b11 4
b1100 &
#569
b110 $
b110 *
b1000110 (
#572
0'
#575
b10 2
#576
b0 +
b100 ,
b110 1
b100 3
b10000 !
b10000 /
1'
b100 4
b10000 &
#577
b111 $
b111 *
b1000111 (
#580
0'
#583
b100 2
#584
b100 +
b10100 !
b10100 /
b1000 3
b111 1
1'
b101 4
b10100 &
#585
b1000 $
b1000 *
b1001000 (
#588
0'
#591
b110 2
#592
b0 +
b0 ,
b0 -
b100 .
b1000 1
b1100 3
b11000 !
b11000 /
1'
b110 4
b11000 &
#593
b1001 $
b1001 *
b1001001 (
#596
0'
#599
b0 2
b100 5
#600
b100 +
b11100 !
b11100 /
b1000 6
b0 3
b1001 1
1'
b111 4
b11100 &
#601
b1010 $
b1010 *
b1001010 (
#604
0'
#607
b10 2
#608
b0 +
b100 ,
b1010 1
b100 3
b100000 !
b100000 /
1'
b1000 4
b100000 &
#609
b1011 $
b1011 *
b1001011 (
#612
0'
#615
b100 2
#616
b100 +
b100100 !
b100100 /
b1000 3
b1011 1
1'
b1001 4
b100100 &
#617
b1100 $
b1100 *
b1001100 (
#620
0'
#623
b110 2
#624
b0 +
b0 ,
b100 -
b1100 1
b1100 3
b101000 !
b101000 /
1'
b1010 4
b101000 &
#625
b1101 $
b1101 *
b1001101 (
#628
0'
#631
b0 2
b110 5
#632
b100 +
b101100 !
b101100 /
b1100 6
b0 3
b1101 1
1'
b1011 4
b101100 &
#633
b1110 $
b1110 *
b1001110 (
#636
0'
#639
b10 2
#640
b0 +
b100 ,
b1110 1
b100 3
b110000 !
b110000 /
1'
b1100 4
b110000 &
#641
b1111 $
b1111 *
b1001111 (
#644
0'
#647
b100 2
#648
b100 +
b110100 !
b110100 /
b1000 3
b1111 1
1'
b1101 4
b110100 &
#649
b101 "
b101 )
b0 $
b0 *
b1010000 (
#652
0'
#655
b110 2
#656
b0 .
b0 -
b0 ,
b0 +
b0 1
b101 0
b1100 3
b111000 !
b111000 /
1'
b1110 4
b111000 &
#657
b1 $
b1 *
b1010001 (
#660
0'
#663
b0 5
b0 2
#664
b101 +
b111100 !
b111100 /
b0 6
b0 3
b1 1
1'
b1111 4
b111100 &
#665
b10 $
b10 *
b1010010 (
#668
0'
#671
b10 2
#672
b0 +
b101 ,
b10 1
b101 3
b0 !
b0 /
1'
b0 4
b0 &
#673
b11 $
b11 *
b1010011 (
#676
0'
#679
b101 2
#680
b101 +
b101 !
b101 /
b1010 3
b11 1
1'
b1 4
b101 &
#681
b100 $
b100 *
b1010100 (
#684
0'
#687
b111 2
#688
b0 +
b0 ,
b101 -
b100 1
b1111 3
b1010 !
b1010 /
1'
b10 4
b1010 &
#689
b101 $
b101 *
b1010101 (
#692
0'
#695
b0 2
b10 5
#696
b101 +
b1111 !
b1111 /
b101 6
b0 3
b101 1
1'
b11 4
b1111 &
#697
b110 $
b110 *
b1010110 (
#700
0'
#703
b10 2
#704
b0 +
b101 ,
b110 1
b101 3
b10100 !
b10100 /
1'
b101 4
b10100 &
#705
b111 $
b111 *
b1010111 (
#708
0'
#711
b101 2
#712
b101 +
b11001 !
b11001 /
b1010 3
b111 1
1'
b110 4
b11001 &
#713
b1000 $
b1000 *
b1011000 (
#716
0'
#719
b111 2
#720
b0 +
b0 ,
b0 -
b101 .
b1000 1
b1111 3
b11110 !
b11110 /
1'
b111 4
b11110 &
#721
b1001 $
b1001 *
b1011001 (
#724
0'
#727
b0 2
b101 5
#728
b101 +
b100011 !
b100011 /
b1010 6
b0 3
b1001 1
1'
b1000 4
b100011 &
#729
b1010 $
b1010 *
b1011010 (
#732
0'
#735
b10 2
#736
b0 +
b101 ,
b1010 1
b101 3
b101000 !
b101000 /
1'
b1010 4
b101000 &
#737
b1011 $
b1011 *
b1011011 (
#740
0'
#743
b101 2
#744
b101 +
b101101 !
b101101 /
b1010 3
b1011 1
1'
b1011 4
b101101 &
#745
b1100 $
b1100 *
b1011100 (
#748
0'
#751
b111 2
#752
b0 +
b0 ,
b101 -
b1100 1
b1111 3
b110010 !
b110010 /
1'
b1100 4
b110010 &
#753
b1101 $
b1101 *
b1011101 (
#756
0'
#759
b0 2
b111 5
#760
b101 +
b110111 !
b110111 /
b1111 6
b0 3
b1101 1
1'
b1101 4
b110111 &
#761
b1110 $
b1110 *
b1011110 (
#764
0'
#767
b10 2
#768
b0 +
b101 ,
b1110 1
b101 3
b111100 !
b111100 /
1'
b1111 4
b111100 &
#769
b1111 $
b1111 *
b1011111 (
#772
0'
#775
b101 2
#776
b101 +
b1000001 !
b1000001 /
b1010 3
b1111 1
1'
b10000 4
b1000001 &
#777
b110 "
b110 )
b0 $
b0 *
b1100000 (
#780
0'
#783
b111 2
#784
b0 .
b0 -
b0 ,
b0 +
b0 1
b110 0
b1111 3
b1000110 !
b1000110 /
1'
b10001 4
b1000110 &
#785
b1 $
b1 *
b1100001 (
#788
0'
#791
b0 5
b0 2
#792
b110 +
b1001011 !
b1001011 /
b0 6
b0 3
b1 1
1'
b10010 4
b1001011 &
#793
b10 $
b10 *
b1100010 (
#796
0'
#799
b11 2
#800
b0 +
b110 ,
b10 1
b110 3
b0 !
b0 /
1'
b0 4
b0 &
#801
b11 $
b11 *
b1100011 (
#804
0'
#807
b110 2
#808
b110 +
b110 !
b110 /
b1100 3
b11 1
1'
b1 4
b110 &
#809
b100 $
b100 *
b1100100 (
#812
0'
#815
b1001 2
#816
b0 +
b0 ,
b110 -
b100 1
b10010 3
b1100 !
b1100 /
1'
b11 4
b1100 &
#817
b101 $
b101 *
b1100101 (
#820
0'
#823
b0 2
b11 5
#824
b110 +
b10010 !
b10010 /
b110 6
b0 3
b101 1
1'
b100 4
b10010 &
#825
b110 $
b110 *
b1100110 (
#828
0'
#831
b11 2
#832
b0 +
b110 ,
b110 1
b110 3
b11000 !
b11000 /
1'
b110 4
b11000 &
#833
b111 $
b111 *
b1100111 (
#836
0'
#839
b110 2
#840
b110 +
b11110 !
b11110 /
b1100 3
b111 1
1'
b111 4
b11110 &
#841
b1000 $
b1000 *
b1101000 (
#844
0'
#847
b1001 2
#848
b0 +
b0 ,
b0 -
b110 .
b1000 1
b10010 3
b100100 !
b100100 /
1'
b1001 4
b100100 &
#849
b1001 $
b1001 *
b1101001 (
#852
0'
#855
b0 2
b110 5
#856
b110 +
b101010 !
b101010 /
b1100 6
b0 3
b1001 1
1'
b1010 4
b101010 &
#857
b1010 $
b1010 *
b1101010 (
#860
0'
#863
b11 2
#864
b0 +
b110 ,
b1010 1
b110 3
b110000 !
b110000 /
1'
b1100 4
b110000 &
#865
b1011 $
b1011 *
b1101011 (
#868
0'
#871
b110 2
#872
b110 +
b110110 !
b110110 /
b1100 3
b1011 1
1'
b1101 4
b110110 &
#873
b1100 $
b1100 *
b1101100 (
#876
0'
#879
b1001 2
#880
b0 +
b0 ,
b110 -
b1100 1
b10010 3
b111100 !
b111100 /
1'
b1111 4
b111100 &
#881
b1101 $
b1101 *
b1101101 (
#884
0'
#887
b0 2
b1001 5
#888
b110 +
b1000010 !
b1000010 /
b10010 6
b0 3
b1101 1
1'
b10000 4
b1000010 &
#889
b1110 $
b1110 *
b1101110 (
#892
0'
#895
b11 2
#896
b0 +
b110 ,
b1110 1
b110 3
b1001000 !
b1001000 /
1'
b10010 4
b1001000 &
#897
b1111 $
b1111 *
b1101111 (
#900
0'
#903
b110 2
#904
b110 +
b1001110 !
b1001110 /
b1100 3
b1111 1
1'
b10011 4
b1001110 &
#905
b111 "
b111 )
b0 $
b0 *
b1110000 (
#908
0'
#911
b1001 2
#912
b0 .
b0 -
b0 ,
b0 +
b0 1
b111 0
b10010 3
b1010100 !
b1010100 /
1'
b10101 4
b1010100 &
#913
b1 $
b1 *
b1110001 (
#916
0'
#919
b0 5
b0 2
#920
b111 +
b1011010 !
b1011010 /
b0 6
b0 3
b1 1
1'
b10110 4
b1011010 &
#921
b10 $
b10 *
b1110010 (
#924
0'
#927
b11 2
#928
b0 +
b111 ,
b10 1
b111 3
b0 !
b0 /
1'
b0 4
b0 &
#929
b11 $
b11 *
b1110011 (
#932
0'
#935
b111 2
#936
b111 +
b111 !
b111 /
b1110 3
b11 1
1'
b1 4
b111 &
#937
b100 $
b100 *
b1110100 (
#940
0'
#943
b1010 2
#944
b0 +
b0 ,
b111 -
b100 1
b10101 3
b1110 !
b1110 /
1'
b11 4
b1110 &
#945
b101 $
b101 *
b1110101 (
#948
0'
#951
b0 2
b11 5
#952
b111 +
b10101 !
b10101 /
b111 6
b0 3
b101 1
1'
b101 4
b10101 &
#953
b110 $
b110 *
b1110110 (
#956
0'
#959
b11 2
#960
b0 +
b111 ,
b110 1
b111 3
b11100 !
b11100 /
1'
b111 4
b11100 &
#961
b111 $
b111 *
b1110111 (
#964
0'
#967
b111 2
#968
b111 +
b100011 !
b100011 /
b1110 3
b111 1
1'
b1000 4
b100011 &
#969
b1000 $
b1000 *
b1111000 (
#972
0'
#975
b1010 2
#976
b0 +
b0 ,
b0 -
b111 .
b1000 1
b10101 3
b101010 !
b101010 /
1'
b1010 4
b101010 &
#977
b1001 $
b1001 *
b1111001 (
#980
0'
#983
b0 2
b111 5
#984
b111 +
b110001 !
b110001 /
b1110 6
b0 3
b1001 1
1'
b1100 4
b110001 &
#985
b1010 $
b1010 *
b1111010 (
#988
0'
#991
b11 2
#992
b0 +
b111 ,
b1010 1
b111 3
b111000 !
b111000 /
1'
b1110 4
b111000 &
#993
b1011 $
b1011 *
b1111011 (
#996
0'
#999
b111 2
#1000
b111 +
b111111 !
b111111 /
b1110 3
b1011 1
1'
b1111 4
b111111 &
#1001
b1100 $
b1100 *
b1111100 (
#1004
0'
#1007
b1010 2
#1008
b0 +
b0 ,
b111 -
b1100 1
b10101 3
b1000110 !
b1000110 /
1'
b10001 4
b1000110 &
#1009
b1101 $
b1101 *
b1111101 (
#1012
0'
#1015
b0 2
b1010 5
#1016
b111 +
b1001101 !
b1001101 /
b10101 6
b0 3
b1101 1
1'
b10011 4
b1001101 &
#1017
b1110 $
b1110 *
b1111110 (
#1020
0'
#1023
b11 2
#1024
b0 +
b111 ,
b1110 1
b111 3
b1010100 !
b1010100 /
1'
b10101 4
b1010100 &
#1025
b1111 $
b1111 *
b1111111 (
#1028
0'
#1031
b111 2
#1032
b111 +
b1011011 !
b1011011 /
b1110 3
b1111 1
1'
b10110 4
b1011011 &
#1033
b1000 "
b1000 )
b0 $
b0 *
b10000000 (
#1036
0'
#1039
b1010 2
#1040
b0 .
b0 -
b0 ,
b0 +
b0 1
b1000 0
b10101 3
b1100010 !
b1100010 /
1'
b11000 4
b1100010 &
#1041
b1 $
b1 *
b10000001 (
#1044
0'
#1047
b0 5
b0 2
#1048
b1000 +
b1101001 !
b1101001 /
b0 6
b0 3
b1 1
1'
b11010 4
b1101001 &
#1049
b10 $
b10 *
b10000010 (
#1052
0'
#1055
b100 2
#1056
b0 +
b1000 ,
b10 1
b1000 3
b0 !
b0 /
1'
b0 4
b0 &
#1057
b11 $
b11 *
b10000011 (
#1060
0'
#1063
b1000 2
#1064
b1000 +
b1000 !
b1000 /
b10000 3
b11 1
1'
b10 4
b1000 &
#1065
b100 $
b100 *
b10000100 (
#1068
0'
#1071
b1100 2
#1072
b0 +
b0 ,
b1000 -
b100 1
b11000 3
b10000 !
b10000 /
1'
b100 4
b10000 &
#1073
b101 $
b101 *
b10000101 (
#1076
0'
#1079
b0 2
b100 5
#1080
b1000 +
b11000 !
b11000 /
b1000 6
b0 3
b101 1
1'
b110 4
b11000 &
#1081
b110 $
b110 *
b10000110 (
#1084
0'
#1087
b100 2
#1088
b0 +
b1000 ,
b110 1
b1000 3
b100000 !
b100000 /
1'
b1000 4
b100000 &
#1089
b111 $
b111 *
b10000111 (
#1092
0'
#1095
b1000 2
#1096
b1000 +
b101000 !
b101000 /
b10000 3
b111 1
1'
b1010 4
b101000 &
#1097
b1000 $
b1000 *
b10001000 (
#1100
0'
#1103
b1100 2
#1104
b0 +
b0 ,
b0 -
b1000 .
b1000 1
b11000 3
b110000 !
b110000 /
1'
b1100 4
b110000 &
#1105
b1001 $
b1001 *
b10001001 (
#1108
0'
#1111
b0 2
b1000 5
#1112
b1000 +
b111000 !
b111000 /
b10000 6
b0 3
b1001 1
1'
b1110 4
b111000 &
#1113
b1010 $
b1010 *
b10001010 (
#1116
0'
#1119
b100 2
#1120
b0 +
b1000 ,
b1010 1
b1000 3
b1000000 !
b1000000 /
1'
b10000 4
b1000000 &
#1121
b1011 $
b1011 *
b10001011 (
#1124
0'
#1127
b1000 2
#1128
b1000 +
b1001000 !
b1001000 /
b10000 3
b1011 1
1'
b10010 4
b1001000 &
#1129
b1100 $
b1100 *
b10001100 (
#1132
0'
#1135
b1100 2
#1136
b0 +
b0 ,
b1000 -
b1100 1
b11000 3
b1010000 !
b1010000 /
1'
b10100 4
b1010000 &
#1137
b1101 $
b1101 *
b10001101 (
#1140
0'
#1143
b0 2
b1100 5
#1144
b1000 +
b1011000 !
b1011000 /
b11000 6
b0 3
b1101 1
1'
b10110 4
b1011000 &
#1145
b1110 $
b1110 *
b10001110 (
#1148
0'
#1151
b100 2
#1152
b0 +
b1000 ,
b1110 1
b1000 3
b1100000 !
b1100000 /
1'
b11000 4
b1100000 &
#1153
b1111 $
b1111 *
b10001111 (
#1156
0'
#1159
b1000 2
#1160
b1000 +
b1101000 !
b1101000 /
b10000 3
b1111 1
1'
b11010 4
b1101000 &
#1161
b1001 "
b1001 )
b0 $
b0 *
b10010000 (
#1164
0'
#1167
b1100 2
#1168
b0 .
b0 -
b0 ,
b0 +
b0 1
b1001 0
b11000 3
b1110000 !
b1110000 /
1'
b11100 4
b1110000 &
#1169
b1 $
b1 *
b10010001 (
#1172
0'
#1175
b0 5
b0 2
#1176
b1001 +
b1111000 !
b1111000 /
b0 6
b0 3
b1 1
1'
b11110 4
b1111000 &
#1177
b10 $
b10 *
b10010010 (
#1180
0'
#1183
b100 2
#1184
b0 +
b1001 ,
b10 1
b1001 3
b0 !
b0 /
1'
b0 4
b0 &
#1185
b11 $
b11 *
b10010011 (
#1188
0'
#1191
b1001 2
#1192
b1001 +
b1001 !
b1001 /
b10010 3
b11 1
1'
b10 4
b1001 &
#1193
b100 $
b100 *
b10010100 (
#1196
0'
#1199
b1101 2
#1200
b0 +
b0 ,
b1001 -
b100 1
b11011 3
b10010 !
b10010 /
1'
b100 4
b10010 &
#1201
b101 $
b101 *
b10010101 (
#1204
0'
#1207
b0 2
b100 5
#1208
b1001 +
b11011 !
b11011 /
b1001 6
b0 3
b101 1
1'
b110 4
b11011 &
#1209
b110 $
b110 *
b10010110 (
#1212
0'
#1215
b100 2
#1216
b0 +
b1001 ,
b110 1
b1001 3
b100100 !
b100100 /
1'
b1001 4
b100100 &
#1217
b111 $
b111 *
b10010111 (
#1220
0'
#1223
b1001 2
#1224
b1001 +
b101101 !
b101101 /
b10010 3
b111 1
1'
b1011 4
b101101 &
#1225
b1000 $
b1000 *
b10011000 (
#1228
0'
#1231
b1101 2
#1232
b0 +
b0 ,
b0 -
b1001 .
b1000 1
b11011 3
b110110 !
b110110 /
1'
b1101 4
b110110 &
#1233
b1001 $
b1001 *
b10011001 (
#1236
0'
#1239
b0 2
b1001 5
#1240
b1001 +
b111111 !
b111111 /
b10010 6
b0 3
b1001 1
1'
b1111 4
b111111 &
#1241
b1010 $
b1010 *
b10011010 (
#1244
0'
#1247
b100 2
#1248
b0 +
b1001 ,
b1010 1
b1001 3
b1001000 !
b1001000 /
1'
b10010 4
b1001000 &
#1249
b1011 $
b1011 *
b10011011 (
#1252
0'
#1255
b1001 2
#1256
b1001 +
b1010001 !
b1010001 /
b10010 3
b1011 1
1'
b10100 4
b1010001 &
#1257
b1100 $
b1100 *
b10011100 (
#1260
0'
#1263
b1101 2
#1264
b0 +
b0 ,
b1001 -
b1100 1
b11011 3
b1011010 !
b1011010 /
1'
b10110 4
b1011010 &
#1265
b1101 $
b1101 *
b10011101 (
#1268
0'
#1271
b0 2
b1101 5
